land.copernicus.theme-4.3-py2.7-nspkg.pth
land/copernicus/theme/__init__.py
land/copernicus/theme/config.py
land/copernicus/theme/configure.zcml
land/copernicus/theme/interfaces.py
land/copernicus/theme/profiles.zcml
land/copernicus/theme/testing.py
land/copernicus/theme/version.txt
land/copernicus/theme/browser/__init__.py
land/copernicus/theme/browser/bootstrap-min.js
land/copernicus/theme/browser/configure.zcml
land/copernicus/theme/browser/design.js
land/copernicus/theme/browser/event_format.py
land/copernicus/theme/browser/events.pt
land/copernicus/theme/browser/footer_info.pt
land/copernicus/theme/browser/homepage.pt
land/copernicus/theme/browser/homepage.py
land/copernicus/theme/browser/news.pt
land/copernicus/theme/browser/publication_display.py
land/copernicus/theme/browser/sticky-menu.js
land/copernicus/theme/browser/survey.pt
land/copernicus/theme/browser/viewlets.py
land/copernicus/theme/browser/theme/fonts/FontAwesome.eot
land/copernicus/theme/browser/theme/fonts/FontAwesome.svg
land/copernicus/theme/browser/theme/fonts/FontAwesome.ttf
land/copernicus/theme/browser/theme/fonts/FontAwesome.woff
land/copernicus/theme/browser/theme/fonts/selection.json
land/copernicus/theme/browser/theme/fonts/style.css
land/copernicus/theme/profiles/default/cssregistry.xml
land/copernicus/theme/profiles/default/jsregistry.xml
land/copernicus/theme/profiles/default/metadata.xml
land/copernicus/theme/profiles/default/profiles.xml
land/copernicus/theme/profiles/default/skins.xml
land/copernicus/theme/profiles/default/theme.xml
land/copernicus/theme/profiles/default/types.xml
land/copernicus/theme/profiles/default/viewlets.xml
land/copernicus/theme/profiles/default/types/Folder.xml
land/copernicus/theme/profiles/default/types/Plone_Site.xml
land/copernicus/theme/skins/copernicus_theme_images/Copernicus_logo_RGB.png
land/copernicus/theme/skins/copernicus_theme_images/EC_logo.gif
land.copernicus.theme-4.3.dist-info/DESCRIPTION.rst
land.copernicus.theme-4.3.dist-info/METADATA
land.copernicus.theme-4.3.dist-info/RECORD
land.copernicus.theme-4.3.dist-info/WHEEL
land.copernicus.theme-4.3.dist-info/metadata.json
land.copernicus.theme-4.3.dist-info/namespace_packages.txt
land.copernicus.theme-4.3.dist-info/top_level.txt
