Metadata-Version: 2.0
Name: land.copernicus.theme
Version: 4.3
Summary: Plone theme for land.copernicus.eu
Home-page: https://github.com/eea/land.copernicus.theme
Author: European Environment Agency
Author-email: webadmin@eea.europa.eu
License: GPL
Keywords: land copernicus eea theme plone zope
Platform: UNKNOWN
Classifier: Framework :: Plone
Classifier: Programming Language :: Python
Provides-Extra: test
Requires-Dist: plone.app.theming
Requires-Dist: setuptools
Provides-Extra: test
Requires-Dist: plone.app.testing; extra == 'test'
Requires-Dist: plone.testing; extra == 'test'
